uncd/UnicodeUtility.py
uncd/__init__.py
uncd-0.16.dist-info/LICENSE
uncd-0.16.dist-info/METADATA
uncd-0.16.dist-info/WHEEL
uncd-0.16.dist-info/entry_points.txt
uncd-0.16.dist-info/top_level.txt
uncd-0.16.dist-info/RECORD
