Metadata-Version: 2.1
Name: uncd
Version: 0.16
Summary: UNKNOWN
Home-page: UNKNOWN
Author: hpencilb
Author-email: haemoglob.j.ben@gmail.com
License: MIT Licence
Platform: UNKNOWN
Classifier: Programming Language :: Python :: 3
Classifier: License :: OSI Approved :: MIT License
Requires-Dist: Click
Requires-Dist: requests
Requires-Dist: BeautifulSoup4
Requires-Dist: lxml
